README.rst
npm.py
setup.cfg
setup.py
rodacom.buildout.npm.egg-info/PKG-INFO
rodacom.buildout.npm.egg-info/SOURCES.txt
rodacom.buildout.npm.egg-info/dependency_links.txt
rodacom.buildout.npm.egg-info/entry_points.txt
rodacom.buildout.npm.egg-info/requires.txt
rodacom.buildout.npm.egg-info/top_level.txt