Metadata-Version: 1.1
Name: rodacom.buildout.npm
Version: 0.6
Summary: A buildout recipe to install NodeJS packages locally using npm
Home-page: https://github.com/rodacom/rodacom.buildout.npm
Author: Michael Lemaire
Author-email: m.lemaire@rodacom.fr
License: Apache Software License
Keywords: buildout zc.buildout recipe nodejs npm
Platform: UNKNOWN
Classifier: Development Status :: 3 - Alpha
Classifier: Framework :: Buildout
Classifier: Intended Audience :: Developers
Classifier: License :: OSI Approved :: Apache Software License
Classifier: Topic :: Software Development :: Build Tools
Classifier: Topic :: Software Development :: Libraries :: Python Modules
Classifier: Operating System :: Unix
Classifier: Programming Language :: Python :: 2.6
Classifier: Programming Language :: Python :: 2.7
Classifier: Programming Language :: Python :: 3
